pyvmess/__about__.py
pyvmess/__init__.py
pyvmess/pyvmess.py
pyvmess-0.0.1.dist-info/METADATA
pyvmess-0.0.1.dist-info/WHEEL
pyvmess-0.0.1.dist-info/licenses/LICENSE.txt
pyvmess-0.0.1.dist-info/RECORD
