Metadata-Version: 2.1
Name: pyvmess
Version: 0.0.1
Summary: a naive implementation to parse raw vmess package
Project-URL: Documentation, https://github.com/fantasquex/pyvmess#readme
Project-URL: Issues, https://github.com/fantasquex/pyvmess/issues
Project-URL: Source, https://github.com/fantasquex/pyvmess
Author-email: Letu Ren <fantasquex@gmail.com>
Keywords: vmess
Classifier: Development Status :: 4 - Beta
Classifier: Programming Language :: Python
Classifier: Programming Language :: Python :: 3.10
Classifier: Programming Language :: Python :: Implementation :: CPython
Requires-Python: >=3.10
Requires-Dist: fnvhash
Requires-Dist: pycryptodome
